{
  "plot_idx": 27,
  "image_path": "C:\\Users\\ziola\\OneDrive\\Documents\\GitHub\\chartocode\\src\\synthetic_plots\\plot_0027.png",
  "image_size": {
    "w": 640,
    "h": 480
  },
  "n_series": 11,
  "n_points": 8,
  "series": [
    {
      "series_idx": 4,
      "symbol_class": 4,
      "symbol_name": "open_triangle",
      "corner_density": 0.0653692353844999,
      "points": [
        {
          "px": 19,
          "py": 431
        },
        {
          "px": 105,
          "py": 456
        },
        {
          "px": 191,
          "py": 453
        },
        {
          "px": 277,
          "py": 448
        },
        {
          "px": 363,
          "py": 432
        },
        {
          "px": 449,
          "py": 207
        },
        {
          "px": 535,
          "py": 107
        },
        {
          "px": 621,
          "py": 101
        }
      ]
    },
    {
      "series_idx": 2,
      "symbol_class": 2,
      "symbol_name": "filled_square",
      "corner_density": 0.9570470026580679,
      "points": [
        {
          "px": 19,
          "py": 398
        },
        {
          "px": 105,
          "py": 398
        },
        {
          "px": 191,
          "py": 398
        },
        {
          "px": 277,
          "py": 400
        },
        {
          "px": 363,
          "py": 392
        },
        {
          "px": 449,
          "py": 250
        },
        {
          "px": 535,
          "py": 193
        },
        {
          "px": 621,
          "py": 197
        }
      ]
    },
    {
      "series_idx": 10,
      "symbol_class": 10,
      "symbol_name": "x_marker",
      "corner_density": 0.9096814486371707,
      "points": [
        {
          "px": 19,
          "py": 449
        },
        {
          "px": 105,
          "py": 442
        },
        {
          "px": 191,
          "py": 444
        },
        {
          "px": 277,
          "py": 425
        },
        {
          "px": 363,
          "py": 332
        },
        {
          "px": 449,
          "py": 141
        },
        {
          "px": 535,
          "py": 58
        },
        {
          "px": 621,
          "py": 77
        }
      ]
    },
    {
      "series_idx": 9,
      "symbol_class": 9,
      "symbol_name": "filled_rhombus",
      "corner_density": 0.18333476966499396,
      "points": [
        {
          "px": 19,
          "py": 413
        },
        {
          "px": 105,
          "py": 401
        },
        {
          "px": 191,
          "py": 404
        },
        {
          "px": 277,
          "py": 380
        },
        {
          "px": 363,
          "py": 316
        },
        {
          "px": 449,
          "py": 186
        },
        {
          "px": 535,
          "py": 133
        },
        {
          "px": 621,
          "py": 115
        }
      ]
    },
    {
      "series_idx": 7,
      "symbol_class": 7,
      "symbol_name": "filled_inv_triangle",
      "corner_density": 0.3723747196357833,
      "points": [
        {
          "px": 19,
          "py": 408
        },
        {
          "px": 105,
          "py": 374
        },
        {
          "px": 191,
          "py": 397
        },
        {
          "px": 277,
          "py": 396
        },
        {
          "px": 363,
          "py": 328
        },
        {
          "px": 449,
          "py": 180
        },
        {
          "px": 535,
          "py": 163
        },
        {
          "px": 621,
          "py": 165
        }
      ]
    },
    {
      "series_idx": 6,
      "symbol_class": 6,
      "symbol_name": "filled_triangle",
      "corner_density": 0.3330666516193206,
      "points": [
        {
          "px": 19,
          "py": 398
        },
        {
          "px": 105,
          "py": 405
        },
        {
          "px": 191,
          "py": 403
        },
        {
          "px": 277,
          "py": 405
        },
        {
          "px": 363,
          "py": 393
        },
        {
          "px": 449,
          "py": 271
        },
        {
          "px": 535,
          "py": 172
        },
        {
          "px": 621,
          "py": 163
        }
      ]
    },
    {
      "series_idx": 1,
      "symbol_class": 1,
      "symbol_name": "open_circle",
      "corner_density": 0.7013695409686748,
      "points": [
        {
          "px": 19,
          "py": 404
        },
        {
          "px": 105,
          "py": 401
        },
        {
          "px": 191,
          "py": 405
        },
        {
          "px": 277,
          "py": 365
        },
        {
          "px": 363,
          "py": 127
        },
        {
          "px": 449,
          "py": 70
        },
        {
          "px": 535,
          "py": 48
        },
        {
          "px": 621,
          "py": 63
        }
      ]
    },
    {
      "series_idx": 3,
      "symbol_class": 3,
      "symbol_name": "open_square",
      "corner_density": 0.19640310908816028,
      "points": [
        {
          "px": 19,
          "py": 435
        },
        {
          "px": 105,
          "py": 448
        },
        {
          "px": 191,
          "py": 432
        },
        {
          "px": 277,
          "py": 447
        },
        {
          "px": 363,
          "py": 361
        },
        {
          "px": 449,
          "py": 235
        },
        {
          "px": 535,
          "py": 124
        },
        {
          "px": 621,
          "py": 78
        }
      ]
    },
    {
      "series_idx": 0,
      "symbol_class": 0,
      "symbol_name": "filled_circle",
      "corner_density": 0.6484972199788831,
      "points": [
        {
          "px": 19,
          "py": 410
        },
        {
          "px": 105,
          "py": 421
        },
        {
          "px": 191,
          "py": 403
        },
        {
          "px": 277,
          "py": 373
        },
        {
          "px": 363,
          "py": 295
        },
        {
          "px": 449,
          "py": 179
        },
        {
          "px": 535,
          "py": 91
        },
        {
          "px": 621,
          "py": 49
        }
      ]
    },
    {
      "series_idx": 8,
      "symbol_class": 8,
      "symbol_name": "open_rhombus",
      "corner_density": 0.8148658231116958,
      "points": [
        {
          "px": 19,
          "py": 419
        },
        {
          "px": 105,
          "py": 425
        },
        {
          "px": 191,
          "py": 428
        },
        {
          "px": 277,
          "py": 310
        },
        {
          "px": 363,
          "py": 151
        },
        {
          "px": 449,
          "py": 146
        },
        {
          "px": 535,
          "py": 133
        },
        {
          "px": 621,
          "py": 148
        }
      ]
    },
    {
      "series_idx": 5,
      "symbol_class": 5,
      "symbol_name": "open_inv_triangle",
      "corner_density": 0.8242574299839418,
      "points": [
        {
          "px": 19,
          "py": 390
        },
        {
          "px": 105,
          "py": 408
        },
        {
          "px": 191,
          "py": 386
        },
        {
          "px": 277,
          "py": 378
        },
        {
          "px": 363,
          "py": 298
        },
        {
          "px": 449,
          "py": 141
        },
        {
          "px": 535,
          "py": 92
        },
        {
          "px": 621,
          "py": 60
        }
      ]
    }
  ]
}